tgctoolbox/__init__.py
tgctoolbox/downloaders.py
tgctoolbox/ffmpeg.py
tgctoolbox/logger.py
tgctoolbox/meta.py
tgctoolbox/operations.py
tgctoolbox/recorder.py
tgctoolbox/settings.py
tgctoolbox/sound.py
tgctoolbox/timing.py
tgctoolbox/vosk.py
tgctoolbox/wait_run.py
tgctoolbox/wrapper.py
tgctoolbox-0.5.dist-info/METADATA
tgctoolbox-0.5.dist-info/WHEEL
tgctoolbox-0.5.dist-info/RECORD
